{
  "timestamp": "2026-02-26T11:43:57.888Z",
  "total": 111,
  "active": 56,
  "groups": 0,
  "dms": 0,
  "crons": 53,
  "topSessions": [
    {
      "name": "Cron: Playing Group - Hourly Leaderboard",
      "tokens": 55284,
      "updated": "Feb 26, 01:00 PM"
    },
    {
      "name": "Cron: Playing Group - Hourly Leaderboard",
      "tokens": 55284,
      "updated": "Feb 26, 01:00 PM"
    },
    {
      "name": "Cron: session-monitor",
      "tokens": 51830,
      "updated": "Feb 26, 01:29 PM"
    },
    {
      "name": "Cron: session-monitor",
      "tokens": 51830,
      "updated": "Feb 26, 01:29 PM"
    },
    {
      "name": "Cron: moltbook-update",
      "tokens": 49380,
      "updated": "Feb 26, 02:32 AM"
    },
    {
      "name": "Cron: moltbook-update",
      "tokens": 49380,
      "updated": "Feb 26, 02:32 AM"
    },
    {
      "name": "Cron: Playing Group - Morning Wakeup",
      "tokens": 48575,
      "updated": "Feb 26, 09:55 AM"
    },
    {
      "name": "Cron: Playing Group - Morning Wakeup",
      "tokens": 48575,
      "updated": "Feb 26, 09:55 AM"
    },
    {
      "name": "whatsapp",
      "tokens": 47126,
      "channel": "whatsapp",
      "updated": "Feb 26, 01:00 PM"
    },
    {
      "name": "whatsapp:g-ai-transformation-guild",
      "tokens": 42286,
      "channel": "whatsapp",
      "updated": "Feb 25, 05:54 PM"
    }
  ]
}